{
"autoplayBgm":false,"autoplayBgs":false,"battleback1Name":"","battleback2Name":"","bgm":{"name":"","pan":0,"pitch":100,"volume":90},"bgs":{"name":"","pan":0,"pitch":100,"volume":90},"disableDashing":false,"displayName":"Baño para ser Feliz","encounterList":[{"regionSet":[],"troopId":57,"weight":5},{"regionSet":[],"troopId":58,"weight":8},{"regionSet":[],"troopId":59,"weight":10}],"encounterStep":10,"height":9,"note":"","parallaxLoopX":false,"parallaxLoopY":false,"parallaxName":"","parallaxShow":true,"parallaxSx":0,"parallaxSy":0,"scrollType":0,"specifyBattleback":false,"tilesetId":8,"width":10,
"data":[7616,7616,7616,7616,7616,7616,7616,7616,7616,7616,7616,7620,7644,7644,7644,7644,7644,7644,7624,7616,7616,7640,7234,7234,7234,7234,7234,7234,7656,7624,7616,7640,7240,7240,7240,7240,7240,7240,7235,7632,7616,7640,1569,1569,1569,1569,1569,1569,7241,7632,7616,7640,1569,1569,1569,1569,1569,1569,1569,7632,7616,7640,1569,1569,1569,1569,1569,1569,7650,7617,7616,7618,7636,7636,7636,7636,7636,7636,7617,7616,7616,7616,7616,7616,7616,7616,7616,7616,7616,7616,0,0,0,0,0,0,0,0,0,0,0,0,0,0,0,0,0,0,0,0,0,0,0,0,0,0,0,0,0,0,0,0,0,0,0,0,0,0,0,0,0,0,0,0,0,0,0,0,0,0,0,0,0,0,0,0,0,0,0,0,0,0,0,0,0,0,0,0,0,0,0,0,0,0,0,0,0,0,0,0,0,0,0,0,0,0,0,0,0,0,0,0,0,0,0,0,0,0,0,0,0,0,0,0,0,0,0,0,0,0,0,0,0,0,0,0,0,0,0,0,0,0,0,0,0,0,0,0,0,0,0,0,0,0,0,0,0,0,0,0,0,0,0,0,0,0,0,0,0,0,0,0,941,0,0,0,0,0,0,0,0,0,0,0,0,0,0,0,0,0,0,0,0,0,0,0,0,0,0,0,0,0,0,0,0,0,0,0,0,0,0,0,0,0,0,0,0,0,0,0,0,0,0,0,0,0,0,0,0,0,0,0,0,929,0,931,0,0,0,0,0,0,0,937,0,939,0,0,0,0,0,0,0,0,0,0,0,0,0,0,0,0,903,942,933,934,0,0,0,0,0,0,0,0,0,0,0,0,0,0,0,0,0,0,0,0,0,0,0,0,0,0,0,0,0,0,0,0,0,0,0,0,0,0,0,0,0,0,0,0,0,0,0,0,0,0,0,0,0,0,0,0,0,0,0,0,0,0,0,0,0,0,5,0,0,0,0,0,0,0,0,0,5,0,0,0,0,0,0,0,0,0,5,0,0,0,0,0,0,0,0,0,0,0,0,0,0,0,0,0,0,0,0,0,0,0,0,0,0,0,0,0,0,0,0,0,0,0,0,0,0,0,0,0,0,0,0,0,0,0,0,0,0,0,0,0,0,0,0,0,0,0,0,0,0,0,0,0,0,0,0,0,0,0,0,0,0,0,0,0,0,0,0,0,0,0,0,0,0,0,0,0,0,0,0,0,0,0,0,0,0,0,0,0,0,0,0,0,0,0,0,0,0,0,0,0,0,0,0,0],
"events":[
null,
{"id":1,"name":"EV001","note":"","pages":[{"conditions":{"actorId":1,"actorValid":false,"itemId":1,"itemValid":false,"selfSwitchCh":"A","selfSwitchValid":false,"switch1Id":1,"switch1Valid":false,"switch2Id":1,"switch2Valid":false,"variableId":1,"variableValid":false,"variableValue":0},"directionFix":false,"image":{"characterIndex":0,"characterName":"","direction":2,"pattern":0,"tileId":0},"list":[{"code":201,"indent":0,"parameters":[0,176,2,6,0,0]},{"code":0,"indent":0,"parameters":[]}],"moveFrequency":3,"moveRoute":{"list":[{"code":0,"parameters":[]}],"repeat":true,"skippable":false,"wait":false},"moveSpeed":3,"moveType":0,"priorityType":0,"stepAnime":false,"through":false,"trigger":1,"walkAnime":true}],"x":8,"y":5},
{"id":2,"name":"EV002","note":"","pages":[{"conditions":{"actorId":1,"actorValid":false,"itemId":1,"itemValid":false,"selfSwitchCh":"A","selfSwitchValid":false,"switch1Id":1,"switch1Valid":false,"switch2Id":1,"switch2Valid":false,"variableId":1,"variableValid":false,"variableValue":0},"directionFix":true,"image":{"tileId":0,"characterName":"!Chest","direction":2,"pattern":1,"characterIndex":1},"list":[{"code":250,"indent":0,"parameters":[{"name":"Chest1","pan":0,"pitch":100,"volume":90}]},{"code":205,"indent":0,"parameters":[0,{"list":[{"code":36},{"code":17},{"code":15,"parameters":[3]},{"code":18},{"code":15,"parameters":[3]},{"code":0}],"repeat":false,"skippable":false,"wait":true}]},{"code":505,"indent":0,"parameters":[{"code":36}]},{"code":505,"indent":0,"parameters":[{"code":17}]},{"code":505,"indent":0,"parameters":[{"code":15,"parameters":[3]}]},{"code":505,"indent":0,"parameters":[{"code":18}]},{"code":505,"indent":0,"parameters":[{"code":15,"parameters":[3]}]},{"code":123,"indent":0,"parameters":["A",0]},{"code":125,"indent":0,"parameters":[0,0,20]},{"code":101,"indent":0,"parameters":["",0,0,2]},{"code":401,"indent":0,"parameters":["20 \\G se encontraron! y una pocion de vida porcentual."]},{"code":126,"indent":0,"parameters":[14,0,0,1]},{"code":0,"indent":0,"parameters":[]}],"moveFrequency":3,"moveRoute":{"list":[{"code":0,"parameters":[]}],"repeat":true,"skippable":false,"wait":false},"moveSpeed":3,"moveType":0,"priorityType":1,"stepAnime":false,"through":false,"trigger":0,"walkAnime":false},{"conditions":{"actorId":1,"actorValid":false,"itemId":1,"itemValid":false,"selfSwitchCh":"A","selfSwitchValid":true,"switch1Id":1,"switch1Valid":false,"switch2Id":1,"switch2Valid":false,"variableId":1,"variableValid":false,"variableValue":0},"directionFix":true,"image":{"tileId":0,"characterName":"!Chest","direction":8,"pattern":1,"characterIndex":1},"list":[{"code":0,"indent":0,"parameters":[]}],"moveFrequency":3,"moveRoute":{"list":[{"code":0,"parameters":[]}],"repeat":true,"skippable":false,"wait":false},"moveSpeed":3,"moveType":0,"priorityType":1,"stepAnime":false,"through":false,"trigger":0,"walkAnime":false}],"x":2,"y":4},
null,
{"id":4,"name":"El Reloj No Funciona","note":"","pages":[{"conditions":{"actorId":1,"actorValid":false,"itemId":1,"itemValid":false,"selfSwitchCh":"A","selfSwitchValid":false,"switch1Id":1,"switch1Valid":false,"switch2Id":1,"switch2Valid":false,"variableId":1,"variableValid":false,"variableValue":0},"directionFix":false,"image":{"characterIndex":0,"characterName":"","direction":2,"pattern":0,"tileId":0},"list":[{"code":101,"indent":0,"parameters":["",0,0,2]},{"code":401,"indent":0,"parameters":["El Reloj no funciona"]},{"code":0,"indent":0,"parameters":[]}],"moveFrequency":3,"moveRoute":{"list":[{"code":0,"parameters":[]}],"repeat":true,"skippable":false,"wait":false},"moveSpeed":3,"moveType":0,"priorityType":1,"stepAnime":false,"through":false,"trigger":0,"walkAnime":true}],"x":2,"y":6}
]
}